[
      {"name":"ASCII код для PrintScreen", "page":"cad6d0f1d8e54f7b"},
      {"name":"Включение и выключение клавиатуры", "page":"221abd5eb97441e3"},
      {"name":"Выставляем горячие клавиши для Delphi приложения", "page":"2388d4e90ee749d8"},
      {"name":"Если нажато более 2-х клавиш одновременно", "page":"dd38ea4fb4d64786"},
      {"name":"Имитация Tab", "page":"c70e2ff696b44931"},
      {"name":"Заставить мерцать индикаторы клавиш CapsLock, NumLock и ScrollLock", "page":"3b47e9cecde64dc8"},
      {"name":"Как отличить нажат правый или левый SHIFT?", "page":"50b3d93fdd1545d6"},
      {"name":"Как отличить нажат правый или левый CTRL?", "page":"4a97756978304b05"},
      {"name":"Как перехватить нажатие TAB?", "page":"eb38e08582f1466c"},
      {"name":"Как отключить комбинацию Alt+Tab", "page":"54bc751d45414a81"},
      {"name":"Как скрыть программу от Alt+Tab?", "page":"93e212b25bb54baf"},
      {"name":"Как заставить кнопку Enter работать наподобие Tab?", "page":"066932a5598d4a19"},
      {"name":"Как послать нажатие клавиши в какое-нибудь окно?", "page":"2a97cc0571e24eeb"},
      {"name":"Как програмно имитировать нажатие Ctrl-Esc?", "page":"151098a7509d405f"},
      {"name":"Как програмно переключить состояние клавиш Num Lock, Caps Lock, Scroll Lock?", "page":"f1aa7aa989f245bd"},
      {"name":"Как узнать состояние клавиши CAPS LOCK?", "page":"763dd11ecd8144bc"},
      {"name":"Как определить, нажата ли в данный момент клавиша Shift, Ctrl или Alt?", "page":"fb065f4228c74079"},
      {"name":"Как определить, нажал ли пользователь клавишу PrintScreen?", "page":"e6797458e49c4797"},
      {"name":"Как глобально перехватить нажатие кнопки PrintScreen?", "page":"9a8cdbbf374942bf"},
      {"name":"Как конвертировать виртуальную клавишу в ASCII-код?", "page":"45eea6ac439b4078"},
      {"name":"Как програмно переключить раскладку клавиатуры?", "page":"2dd34a4928b14c1f"},
      {"name":"Как запретить Ctrl-Alt-Del?", "page":"7a56693b5c3448aa"},
      {"name":"Как отловить правый Enter (NumPad)?", "page":"5db7b6bc66d94d04"},
      {"name":"Как заставить дополнительную клавиатуру всегда работать в режиме цифр?", "page":"624480b809af4e07"},
      {"name":"Как отловить изменение раскладки клавиатуры?", "page":"c0476d83efb44299"},
      {"name":"Как очистить буфер клавиатуры?", "page":"4f4b77d00a9648b6"},
      {"name":"Как перехватить нажатия функциональных клавиш и стрелок?", "page":"ea65cac7d17e4147"},
      {"name":"Как узнать о нажатии NON-MENU клавиши в момент, когда меню показано?", "page":"9917448f40844751"},
      {"name":"Как сделать клавишу-акселератор (keyboard shortcut) компонету, у которого нет заголовка?", "page":"7876857a868b4cd3"},
      {"name":"Как определить нажаты ли клавиши Shift, Alt или Ctrl в какой-либо момент времени?", "page":"1a0b9820163e4f3a"},
      {"name":"Как выполнять другую команду по нажатию на кнопку, если зажата клавиша Shift?", "page":"40efe14400fb4f52"},
      {"name":"Как определить нажатие определенной клавиши во время загрузки приложения?", "page":"3df9afb58e614771"},
      {"name":"Как отловить правый Enter (NumPad)", "page":"3d2b0664131945c8"},
      {"name":"Коды виртуальных клавиш", "page":"e596435ff6ce41c8"},
      {"name":"Регистрируем горячие клавиши", "page":"8de2e6542cd149e7"},
      {"name":"Симфония на клавиатуре (статья)", "page":"ebf34df14c29475e"},
      {"name":"Состояние кнопки Insert", "page":"b7c1f35e2a684c5d"},
      {"name":"Оперировать с цифровой частью клавиатуры всегда как будто NumLock занят", "page":"ca1afbdb95894544"},
      {"name":"Определение нажатия определенной клавиши во время загрузки приложения", "page":"78324c556e6d4b5d"},
      {"name":"Перехватить нажатие клавиши на клавиатуре", "page":"fc6d0837cb584ea9"},
      {"name":"Переключение раскладки клавиатуры для приложения", "page":"1b7ed04d19f44df8"},
      {"name":"Получение типа клавиатуры", "page":"f5fbffdf8c594209"},
      {"name":"Програмная эмуляция нажатия клавиш", "page":"95df5024c6454e90"},
      {"name":"Программно нажимаем Print Screen", "page":"879fc24946fc4c8e"}
]
