[
      {"name":"Как использовать базу данных BDE, не указывая её имени?", "page":"a6e5889cad714473.html"},
      {"name":"Как узнать физическое расположение локальной БД по Alias?", "page":"e4d71efd5b2347e4.html"},
      {"name":"Как проверять корректность доступа к базе данных?", "page":"41e0d69ba7b44e60.html"},
      {"name":"Как узнать путь базы данных и её имя?", "page":"44032a475a8f4cb6.html"},
      {"name":"Как зарегистрировать базу данных (BDE)?", "page":"8b53f98c44d34ca4.html"},
      {"name":"Определение типа базы данных", "page":"403a3e55e77048d2.html"},
      {"name":"Как очистить базу данных, оставив только структуру?", "page":"bfb009204fee4f90.html"},
      {"name":"Как перейти к указанной записи в БД", "page":"da67786666f8490f.html"},
      {"name":"Функция для быстрого копирования таблиц вместе со всеми дополнительными файлами", "page":"7f677a06831c4b47.html"}
]
